{
	"imageName": "Lavaridge_Town_E.png",
	"warps": 
	[
		{
			"altName": "PokeCenter",
			"coordString": "128,48,191,111"
		},
		{
			"altName": "PokeMart",
			"coordString": "224,40,287,95"
		},
		{
			"altName": "Gym",
			"coordString": "32,176,127,255"
		},
		{
			"altName": "House 1",
			"coordString": "176,192,239,255"
		},
		{
			"altName": "House 2",
			"coordString": "240,192,303,255"
		},
		{
			"altName": "Hot Spring",
			"coordString": "36,32,123,111"
		},
		{
			"altName": "Jagged Pass",
			"coordString": "12,382,143,409"
		},
		{
			"altName": "Fiery Path S",
			"coordString": "12,432,149,459"
		},
		{
			"altName": "Cable Car Station",
			"coordString": "12,482,209,509"
		},
		{
			"altName": "Mirage Tower",
			"coordString": "12,532,155,559"
		},
		{
			"altName": "Desert Ruins",
			"coordString": "12,582,155,609"
		}
	]
}